retriefine/__init__.py
retriefine/py.typed
retriefine-0.0.1.dist-info/WHEEL
retriefine-0.0.1.dist-info/METADATA
retriefine-0.0.1.dist-info/RECORD
